proxy/__init__.py
proxy/proxy.py
proxy_handler-1.0.1.dist-info/licenses/LICENSE
proxy_handler-1.0.1.dist-info/METADATA
proxy_handler-1.0.1.dist-info/WHEEL
proxy_handler-1.0.1.dist-info/top_level.txt
proxy_handler-1.0.1.dist-info/RECORD
