Metadata-Version: 2.4
Name: proxy-handler
Version: 1.0.1
Summary: simple proxy class
Author-email: olezx <olekzx@python.com>
Project-URL: Homepage, https://github.com/olekzx/proxy-handler
Project-URL: Bug Tracker, https://github.com/olekzx/proxy-handler/issues
Keywords: python,proxy,socks5,https,http,requests,httpx,async
Classifier: License :: OSI Approved :: MIT License
Classifier: Programming Language :: Python
Classifier: Programming Language :: Python :: 3
Requires-Python: >=3.10
License-File: LICENSE
Requires-Dist: httpx>=0.27.0
Dynamic: license-file
